sine.threads-0.1.6-py2.7-nspkg.pth
sine/threads/__init__.py
sine/threads/__version__.py
sine/threads/core.py
sine/threads/tests.py
sine.threads-0.1.6.dist-info/DESCRIPTION.rst
sine.threads-0.1.6.dist-info/METADATA
sine.threads-0.1.6.dist-info/RECORD
sine.threads-0.1.6.dist-info/WHEEL
sine.threads-0.1.6.dist-info/metadata.json
sine.threads-0.1.6.dist-info/namespace_packages.txt
sine.threads-0.1.6.dist-info/top_level.txt
