Metadata-Version: 2.0
Name: sine.threads
Version: 0.1.6
Summary: stoppable and restartable thread simply using an event
Home-page: https://github.com/SineObama/
Author: Xian Zheng
Author-email: 714186139@qq.com
License: MIT
Platform: UNKNOWN
Classifier: License :: OSI Approved :: MIT License
Classifier: Programming Language :: Python
Classifier: Programming Language :: Python :: 2.7
Classifier: Programming Language :: Python :: Implementation :: CPython
Classifier: Programming Language :: Python :: Implementation :: PyPy
Requires-Python: >=2.7.0
